[
    {
        "id": "autonomous-drone",
        "title": "Autonomous Drone",
        "image": "./assets/img/kaedegami2.png",
        "description": "Exploratory drone that created to explore SLAM, Odometry, and Reinforcement Learning, inspired by Turtlebot.",
        "githubUrl": "https://github.com/sunghyuneun/Autonomous-Drone",
        "tags": ["ROS2", "SLAM", "RL", "Python", "C++", "Raspberry Pi", "Arduino", "Linux", "Solidworks"],
        "featured": true
    },
    {
        "id": "ml-projects",
        "title": "Machine Learning Projects",
        "image": "./assets/img/comolake.jpg",
        "description": "Reinforcement Learning. Starting with HalfCheetah and CartPole.",
        "githubUrl": "https://github.com/sunghyuneun/ML-Projects",
        "tags": ["Python", "RL"],
        "featured": true
    },
    {
        "id": "balancing-robot",
        "title": "Self Balancing Robot",
        "image": "./assets/img/balancing_bot/balancing-robot.png",
        "description": "Self Balancing Robot. Currently PID Controller in Gazebo, RL controller being created, physical deployed model is planned.",
        "githubUrl": "https://github.com/sunghyuneun/Balancing-Robot",
        "tags": ["Gazebo", "PID Control", "C++", "Altium", "Arduino","Linux"],
        "featured": true
    },
    {
        "id": "tbots-work",
        "title": "Thunderbots Contributions",
        "image": "./assets/img/thunderbots/thunderbotsicon.jpeg",
        "description": "My work for the UBC Thunderbots Electrical Subteam.",
        "githubUrl": "https://github.com/sunghyuneun/Thunderbots-Contributions",
        "tags": ["Altium", "LTSpice", "Control Theory"],
        "featured": true
    },
    {
        "id": "rover-work",
        "title": "Rover Contributions",
        "image": "./assets/img/rover/ubcrover.jpeg",
        "description": "My work for the UBC Rover Arm Subteam.",
        "githubUrl": "https://github.com/sunghyuneun/Rover-Contributions",
        "tags": ["SolidWorks", "CAD", "FEA Analysis"],
        "featured": false
    },
    {
        "id": "autonomous-turret",
        "title": "Autonomous Turret",
        "image": "./assets/img/autonomous_turret/autonomous-turret.png",
        "description": "Raspberry Pi controlled Autonomous Turret built in 3 weeks.",
        "githubUrl": "https://github.com/sunghyuneun/Autonomous-Turret",
        "tags": ["Raspberry Pi", "ROS2", "Python", "OpenCV","C++","Arduino", "Linux", "Solidworks"],
        "featured": true
    },
    {
        "id": "misc-projects",
        "title": "Miscellaneous Projects",
        "image": "./assets/img/sou.png",
        "description": "Everything else I've created, that's too small to get its own post.",
        "githubUrl": "https://github.com/sunghyuneun/Blaze-Robotics",
        "tags": ["Altium", "Python"],
        "featured": false
    }
]
